azure/mgmt/billing/__init__.py
azure/mgmt/billing/_billing_management_client.py
azure/mgmt/billing/_configuration.py
azure/mgmt/billing/_patch.py
azure/mgmt/billing/_serialization.py
azure/mgmt/billing/_version.py
azure/mgmt/billing/py.typed
azure/mgmt/billing/aio/__init__.py
azure/mgmt/billing/aio/_billing_management_client.py
azure/mgmt/billing/aio/_configuration.py
azure/mgmt/billing/aio/_patch.py
azure/mgmt/billing/aio/operations/__init__.py
azure/mgmt/billing/aio/operations/_address_operations.py
azure/mgmt/billing/aio/operations/_agreements_operations.py
azure/mgmt/billing/aio/operations/_associated_tenants_operations.py
azure/mgmt/billing/aio/operations/_available_balances_operations.py
azure/mgmt/billing/aio/operations/_billing_accounts_operations.py
azure/mgmt/billing/aio/operations/_billing_permissions_operations.py
azure/mgmt/billing/aio/operations/_billing_profiles_operations.py
azure/mgmt/billing/aio/operations/_billing_property_operations.py
azure/mgmt/billing/aio/operations/_billing_requests_operations.py
azure/mgmt/billing/aio/operations/_billing_role_assignments_operations.py
azure/mgmt/billing/aio/operations/_billing_role_definition_operations.py
azure/mgmt/billing/aio/operations/_billing_subscriptions_aliases_operations.py
azure/mgmt/billing/aio/operations/_billing_subscriptions_operations.py
azure/mgmt/billing/aio/operations/_customers_operations.py
azure/mgmt/billing/aio/operations/_departments_operations.py
azure/mgmt/billing/aio/operations/_enrollment_accounts_operations.py
azure/mgmt/billing/aio/operations/_invoice_sections_operations.py
azure/mgmt/billing/aio/operations/_invoices_operations.py
azure/mgmt/billing/aio/operations/_operations.py
azure/mgmt/billing/aio/operations/_partner_transfers_operations.py
azure/mgmt/billing/aio/operations/_patch.py
azure/mgmt/billing/aio/operations/_payment_methods_operations.py
azure/mgmt/billing/aio/operations/_policies_operations.py
azure/mgmt/billing/aio/operations/_products_operations.py
azure_mgmt_billing-7.0.0.dist-info/LICENSE
azure_mgmt_billing-7.0.0.dist-info/METADATA
azure_mgmt_billing-7.0.0.dist-info/WHEEL
azure_mgmt_billing-7.0.0.dist-info/top_level.txt
azure_mgmt_billing-7.0.0.dist-info/RECORD
